{
  "basic_statistics": {
    "partidos": 2,
    "apodo": "Bag",
    "puntos": 6,
    "efectividad": 1.0,
    "promedio": 0.5,
    "ganados": 2,
    "empatados": 0,
    "perdidos": 0
  },
  "winning_streak_statistics": {
    "empieza": "2025-09-03",
    "termina": "2025-09-10",
    "extension": 2,
    "puntos acumulados": 6,
    "victorias": 2,
    "empates": 0,
    "actual": true
  },
  "present_streak_statistics": {
    "empieza": "2025-09-03",
    "termina": "2025-09-10",
    "extension": 2,
    "actual": true
  },
  "last_5": {
    "2025-09-10": "G",
    "2025-09-03": "G",
    "2025-08-27": "A"
  },
  "balance_vs": {
    "Cesano, Leandro": 2,
    "Ruiz, Mariano": 2,
    "Chagay, Alexis": 1,
    "Tosi, Marcelo": 1,
    "Daher, Camilo": 1,
    "Gimenez, Yamil": 1,
    "Lombardo, Juan Pablo": 1,
    "Recalde, Facundo": 1
  },
  "best_partner": {
    "Lombardo, Emiliano": 2,
    "Caballero, Alejandro": 1,
    "Chagay, Alexis": 1,
    "Lombardo, Juan Pablo": 1,
    "Nuñez, Cesar": 1,
    "Ponce, Martin": 1,
    "Tosi, Marcelo": 1
  },
  "worse_partner": {},
  "paternity": {
    "Cesano, Leandro": 2,
    "Chagay, Alexis": 1,
    "Ruiz, Mariano": 2,
    "Tosi, Marcelo": 1,
    "Daher, Camilo": 1,
    "Gimenez, Yamil": 1,
    "Lombardo, Juan Pablo": 1,
    "Recalde, Facundo": 1
  },
  "filiation": {}
}